jstreams/__init__.py
jstreams/__init__.pyi
jstreams/ioc.py
jstreams/ioc.pyi
jstreams/match.py
jstreams/match.pyi
jstreams/noop.py
jstreams/noop.pyi
jstreams/predicate.py
jstreams/predicate.pyi
jstreams/py.typed
jstreams/rx.py
jstreams/rx.pyi
jstreams/stream.py
jstreams/stream.pyi
jstreams/thread.py
jstreams/thread.pyi
jstreams/timer.py
jstreams/timer.pyi
jstreams/tryOpt.py
jstreams/tryOpt.pyi
jstreams/tuples.py
jstreams/tuples.pyi
jstreams/utils.py
jstreams/utils.pyi
jstreams-2025.3.1.dist-info/LICENSE
jstreams-2025.3.1.dist-info/METADATA
jstreams-2025.3.1.dist-info/WHEEL
jstreams-2025.3.1.dist-info/top_level.txt
jstreams-2025.3.1.dist-info/RECORD
