Metadata-Version: 2.2
Name: jstreams
Version: 2025.3.1
Summary: A package providing streams and optional functionality similar to Java streams and optionals, a vavr.io Try minimal implementation, threading utilities such as JavaScript-like setTimer and setInterval,1 as well as a basic implementation of ReactiveX and a dependency injection framework.
Author: Cristian Trohin
Author-email: Cristian Trohin <cristi.trohin@gmail.com>
Project-URL: Homepage, https://github.com/ctrohin/jstream
Project-URL: Issues, https://github.com/ctrohin/jstream/issues
Classifier: Programming Language :: Python :: 3
Classifier: License :: OSI Approved :: MIT License
Classifier: Operating System :: OS Independent
Requires-Python: >=3.9
License-File: LICENSE
Dynamic: author
